hamster_gtk/__init__.py
hamster_gtk/hamster_gtk.py
hamster_gtk/helpers.py
hamster_gtk/misc/__init__.py
hamster_gtk/misc/dialogs/__init__.py
hamster_gtk/misc/dialogs/date_range_select_dialog.py
hamster_gtk/misc/dialogs/edit_fact_dialog.py
hamster_gtk/misc/dialogs/error_dialog.py
hamster_gtk/misc/dialogs/hamster_about_dialog.py
hamster_gtk/overview/__init__.py
hamster_gtk/overview/dialogs.py
hamster_gtk/overview/widgets/__init__.py
hamster_gtk/overview/widgets/charts.py
hamster_gtk/overview/widgets/fact_grid.py
hamster_gtk/overview/widgets/misc.py
hamster_gtk/preferences/__init__.py
hamster_gtk/preferences/preferences_dialog.py
hamster_gtk/preferences/widgets/__init__.py
hamster_gtk/preferences/widgets/combo_file_chooser.py
hamster_gtk/preferences/widgets/config_widget.py
hamster_gtk/preferences/widgets/hamster_combo_box_text.py
hamster_gtk/preferences/widgets/hamster_spin_button.py
hamster_gtk/preferences/widgets/time_entry.py
hamster_gtk/resources/css/hamster-gtk.css
hamster_gtk/tracking/__init__.py
hamster_gtk/tracking/screens.py
hamster_gtk-0.11.0.dist-info/DESCRIPTION.rst
hamster_gtk-0.11.0.dist-info/METADATA
hamster_gtk-0.11.0.dist-info/RECORD
hamster_gtk-0.11.0.dist-info/WHEEL
hamster_gtk-0.11.0.dist-info/entry_points.txt
hamster_gtk-0.11.0.dist-info/metadata.json
hamster_gtk-0.11.0.dist-info/top_level.txt
tests/__init__.py
tests/conftest.py
tests/factories.py
tests/test_hamster-gtk.py
tests/test_helpers.py
tests/test_minimal.py
tests/misc/__init__.py
tests/misc/conftest.py
tests/misc/test_dialogs.py
tests/overview/__init__.py
tests/overview/conftest.py
tests/overview/test_dialogs.py
tests/overview/test_widgets.py
tests/preferences/__init__.py
tests/preferences/conftest.py
tests/preferences/test_preferences_dialog.py
tests/preferences/widgets/__init__.py
tests/preferences/widgets/conftest.py
tests/preferences/widgets/test_combo_file_chooser.py
tests/preferences/widgets/test_config_widget.py
tests/preferences/widgets/test_hamster_combo_box_text.py
tests/preferences/widgets/test_hamster_spin_button.py
tests/preferences/widgets/test_time_entry.py
tests/tracking/__init__.py
tests/tracking/conftest.py
tests/tracking/test_screens.py
