Metadata-Version: 2.0
Name: hamster-gtk
Version: 0.11.0
Summary: A GTK interface to the hamster time tracker.
Home-page: https://github.com/projecthamster/hamster-gtk
Author: Eric Goller
Author-email: eric.goller@projecthamster.org
License: GPL3
Keywords: hamster-gtk
Platform: UNKNOWN
Classifier: Development Status :: 2 - Pre-Alpha
Classifier: Intended Audience :: End Users/Desktop
Classifier: License :: OSI Approved :: GNU General Public License v3 (GPLv3)
Classifier: Natural Language :: English
Classifier: Programming Language :: Python :: 2
Classifier: Programming Language :: Python :: 2.7
Classifier: Programming Language :: Python :: 3
Classifier: Programming Language :: Python :: 3.5
Requires-Dist: hamster-lib
